pisnp/__init__.py
pisnp/__main__.py
pisnp/draft.py
pisnp/problem_generator.py
pisnp/solver.py
pisnp/exact_cover/__init__.py
pisnp/exact_cover/exact_cover_solver.py
pisnp/sudoku/__init__.py
pisnp/sudoku/sudoku_generator.py
pisnp/sudoku/sudoku_solver.py
pisnp/traveling_salesman/__init__.py
pisnp/traveling_salesman/traveling_salesman_generator.py
pisnp/traveling_salesman/traveling_salesman_solver.py
pisnp/utility/__init__.py
pisnp/utility/timer.py
pisnp-2022.6.3.dist-info/LICENSE.txt
pisnp-2022.6.3.dist-info/METADATA
pisnp-2022.6.3.dist-info/WHEEL
pisnp-2022.6.3.dist-info/entry_points.txt
pisnp-2022.6.3.dist-info/top_level.txt
pisnp-2022.6.3.dist-info/RECORD
