Metadata-Version: 2.1
Name: pisnp
Version: 2022.6.3
Summary: P is NP? (Polynomial is Non-polynomial?)
Author-email: "谢方圆 (XIE Fangyuan)" <xie.fangyuan@foxmail.com>
License: MIT License
Project-URL: Homepage, https://gitee.com/xie-fangyuan/pisnp
Keywords: polynomial,non-polynomial
Classifier: Programming Language :: Python :: 3.10
Classifier: Operating System :: OS Independent
Classifier: License :: OSI Approved :: MIT License
Requires-Python: >=3.10
License-File: LICENSE.txt
Requires-Dist: matplotlib
Requires-Dist: numpy
Requires-Dist: sty
Provides-Extra: dev
Requires-Dist: bumpver ; extra == 'dev'
Requires-Dist: build ; extra == 'dev'
Requires-Dist: twine ; extra == 'dev'
